Metadata-Version: 2.4
Name: mcp-server-2
Version: 0.1.0
Summary: Add your description here
Author-email: xiazhonghui <1917523457@qq.com>
Requires-Python: >=3.13
Requires-Dist: mcp[cli]>=1.11.0
